yagooglesearch/__init__.py
yagooglesearch/result_languages.txt
yagooglesearch/user_agents.txt
yagooglesearch-1.9.0.dist-info/LICENSE
yagooglesearch-1.9.0.dist-info/METADATA
yagooglesearch-1.9.0.dist-info/WHEEL
yagooglesearch-1.9.0.dist-info/top_level.txt
yagooglesearch-1.9.0.dist-info/RECORD
