Metadata-Version: 2.1
Name: yagooglesearch
Version: 1.9.0
Summary: A Python library for executing intelligent, realistic-looking, and tunable Google searches.
Author-email: Brennon Thomas <info@opsdisk.com>
License: BSD 3-Clause License
Project-URL: Homepage, https://github.com/opsdisk/yagooglesearch
Project-URL: Documentation, https://github.com/opsdisk/yagooglesearch
Project-URL: Repository, https://github.com/opsdisk/yagooglesearch
Keywords: python,google,search,googlesearch
Classifier: Programming Language :: Python
Requires-Python: >=3.6
License-File: LICENSE
Requires-Dist: beautifulsoup4 >=4.9.3
Requires-Dist: requests >=2.31.0
Requires-Dist: requests[socks]
